Metadata-Version: 2.1
Name: djsonREST
Version: 0.2.15
Summary: Simply build a powerful JSON-REST-API with django
Home-page: https://git.voltane.eu/voltane/pypi/djsonrest
Author: Manuel Stingl
Author-email: opensource@voltane.eu
License: GNU GPLv3
Platform: UNKNOWN
Classifier: Programming Language :: Python :: 3
Classifier: License :: OSI Approved :: GNU General Public License v3 or later (GPLv3+)
Classifier: Operating System :: OS Independent
Classifier: Framework :: Django
Classifier: Framework :: Django :: 2.0
Classifier: Framework :: Django :: 2.1
Classifier: Framework :: Django :: 2.2
Classifier: Framework :: Django :: 3.0
Classifier: Development Status :: 3 - Alpha
Requires-Python: >=3.6
Requires-Dist: django (>=2.0)
Requires-Dist: python-jose (>=3.1.0)
Requires-Dist: djutils (>=1.0.7)
